boyleworkflow/__init__.py
boyleworkflow/cli.py
boyleworkflow/config.py
boyleworkflow/core.py
boyleworkflow/log.py
boyleworkflow/make.py
boyleworkflow/runcalc.py
boyleworkflow/storage.py
boyleworkflow/task.py
boyleworkflow-0.1.2.dist-info/AUTHORS.rst
boyleworkflow-0.1.2.dist-info/LICENSE
boyleworkflow-0.1.2.dist-info/METADATA
boyleworkflow-0.1.2.dist-info/WHEEL
boyleworkflow-0.1.2.dist-info/entry_points.txt
boyleworkflow-0.1.2.dist-info/top_level.txt
boyleworkflow-0.1.2.dist-info/RECORD
