Metadata-Version: 2.1
Name: boyleworkflow
Version: 0.1.2
Summary: A tool for provenance and caching in computational workflows.
Home-page: https://github.com/boyleworkflow/boyle
Author: Rasmus Einarsson and Jonatan Kallus
Author-email: mr@rasmuseinarsson.se, mr@jkallus.se
License: LGPLv3
Keywords: boyle
Platform: UNKNOWN
Classifier: Development Status :: 2 - Pre-Alpha
Classifier: Intended Audience :: Developers
Classifier: License :: OSI Approved :: GNU Lesser General Public License v3 (LGPLv3)
Classifier: Natural Language :: English
Classifier: Programming Language :: Python :: 3
Classifier: Programming Language :: Python :: 3.6
Classifier: Programming Language :: Python :: 3.7
Requires-Dist: Click (>=7.0)
